needagx/__init__.py
needagx-1.1.2.dist-info/METADATA
needagx-1.1.2.dist-info/WHEEL
needagx-1.1.2.dist-info/RECORD
