Metadata-Version: 2.1
Name: needagx
Version: 1.1.2
Summary: A sample project depending no AGX, using agxver to solve deps
Author: Jonas Andersson
Author-email: jonas.andersson@algoryx.com
Requires-Python: >=3.8
Classifier: Programming Language :: Python :: 3
Classifier: Programming Language :: Python :: 3.8
Classifier: Programming Language :: Python :: 3.9
Classifier: Programming Language :: Python :: 3.10
Classifier: Programming Language :: Python :: 3.11
Requires-Dist: agxver (==2.36.1.2)
